{"nombre_pdf": "avigilon-h5a-rugged-ptz-camera-datasheet-es", "modelo": "H5A PTZ Resistente", "proveedor": "Avigilon", "equipo": "camara", "precio": 1049.21, "n_paginas": 6, "tablas": ["[MATERIAL] camara [MODELO] H5A PTZ Resistente [PROVEEDOR] Avigilon [TABLA] ['RENDIMIENTO DE IMAGEN: Sensor de imagen. RENDIMIENTO DE IMAGEN: Sensor de imagen. 2,0 MP: CMOS de barrido progresivo 1/2,8\u201d. 4,0 MP: Sensor CMOS tipo \u201cExmor R\u201d de 1/2,5\u201d. 8,0 MP: Sensor CMOS tipo \u201cExmor R\u201d de 1/2,5\u201d.', 'RENDIMIENTO DE IMAGEN: P\u00edxeles activos (H x V). RENDIMIENTO DE IMAGEN: P\u00edxeles activos (H x V). 2,0 MP: 1937 (H) \u00d7 1097 (V). 4,0 MP: 2688 (H) \u00d7 1512 (V). 8,0 MP: 3840 (H) \u00d7 2160 (V).', 'RENDIMIENTO DE IMAGEN: \u00c1rea de digitalizaci\u00f3n (H x V). RENDIMIENTO DE IMAGEN: \u00c1rea de digitalizaci\u00f3n (H x V). 2,0 MP: 4,8 mm (H) \u00d7 2,7 mm (V); 0,189\" (H) \u00d7 0,106\" (V). 4,0 MP: 6,22 mm (H) \u00d7 3,50 mm (V); 0,245\" (H) \u00d7 0,137\" (V). 8,0 MP: 6,22 mm (H) \u00d7 3,50 mm (V); 0,245\" (H) \u00d7 0,137\" (V).', 'RENDIMIENTO DE IMAGEN: Distancia m\u00e1xima de iluminaci\u00f3n IR. RENDIMIENTO DE IMAGEN: AVUEI8AA. 2,0 MP: 100 m (328 pies). 4,0 MP: 30 m (98 pies). 8,0 MP: 30 m (98 pies).', 'RENDIMIENTO DE IMAGEN: Distancia m\u00e1xima de iluminaci\u00f3n IR. RENDIMIENTO DE IMAGEN: AVUEI8AAP. 2,0 MP: 200 m (656 pies). 4,0 MP: 75 m (246 pies). 8,0 MP: 75 m (246 pies).', 'RENDIMIENTO DE IMAGEN: Distancia m\u00e1xima de iluminaci\u00f3n IR. RENDIMIENTO DE IMAGEN: AVUEI9AA. 2,0 MP: 75 m (246 pies). 4,0 MP: 20 m (66 pies). 8,0 MP: 20 m (66 pies).', 'RENDIMIENTO DE IMAGEN: Distancia m\u00e1xima de iluminaci\u00f3n IR. RENDIMIENTO DE IMAGEN: AVUEIWAA. 2,0 MP: 150 m (492 pies). 4,0 MP: 50 m (164 pies). 8,0 MP: 50 m (164 pies).', 'RENDIMIENTO DE IMAGEN: Distancia m\u00e1xima de iluminaci\u00f3n IR. RENDIMIENTO DE IMAGEN: AVUEIWAAP. 2,0 MP: 200 m (656 pies). 4,0 MP: 100 m (328 pies). 8,0 MP: 100 m (328 pies).', 'RENDIMIENTO DE IMAGEN: Iluminaci\u00f3n m\u00ednima. RENDIMIENTO DE IMAGEN: Iluminaci\u00f3n m\u00ednima. 2,0 MP: 0,03 lux (F/1,6) en modo color; 0,02 lux (F/1,6) en modo monocromo. 4,0 MP: 0,3 lux (F/2,0) en modo color; 0,09 lux (F/2,0) en modo monocromo. 8,0 MP: 0,3 lux (F/2,0) en modo color; 0,09 lux (F/2,0) en modo monocromo.', 'RENDIMIENTO DE IMAGEN: Rango din\u00e1mico. RENDIMIENTO DE IMAGEN: Rango din\u00e1mico. 2,0 MP: M\u00e1s de 120 dB. 4,0 MP: 100 dB. 8,0 MP: 100 dB.', 'RENDIMIENTO DE IMAGEN: Velocidad de imagen. RENDIMIENTO DE IMAGEN: Velocidad de imagen. 2,0 MP: Hasta 60 fps. 4,0 MP: Hasta 30 fps. 8,0 MP: Hasta 30 fps.', 'RENDIMIENTO DE IMAGEN: Relaci\u00f3n de aspecto (Escalado de resoluci\u00f3n). RENDIMIENTO DE IMAGEN: Relaci\u00f3n de aspecto (Escalado de resoluci\u00f3n). 2,0 MP: Hasta (16:9) 384\u00d7216 o (5:4) 320\u00d7256. 4,0 MP: Hasta (16:9) 384\u00d7216 o (5:4) 320\u00d7256. 8,0 MP: Hasta (16:9) 384\u00d7216 o (5:4) 320\u00d7256.', 'RENDIMIENTO DE IMAGEN: Filtro de reducci\u00f3n de ruido 3D. RENDIMIENTO DE IMAGEN: Filtro de reducci\u00f3n de ruido 3D. 2,0 MP: S\u00ed. 4,0 MP: S\u00ed. 8,0 MP: S\u00ed.']", "[MATERIAL] camara [MODELO] H5A PTZ Resistente [PROVEEDOR] Avigilon [TABLA] ['OBJETIVO: Objetivo. OBJETIVO: Objetivo. 2,0 MP: De 4,25 a 170 mm, F/1,6 - F/4,95, enfoque autom\u00e1tico. 4,0 MP: De 4,4 a 88 mm, F/2,0 - F/3,8, enfoque autom\u00e1tico. 8,0 MP: De 4,4 a 88 mm, F/2,0 - F/3,8, enfoque autom\u00e1tico.', 'OBJETIVO: \u00c1ngulo de visi\u00f3n. OBJETIVO: Horizontal. 2,0 MP: 66,35\u00b0 - 1,9\u00b0. 4,0 MP: 69,7\u00b0 - 2,2\u00b0. 8,0 MP: 69,7\u00b0 - 2,2\u00b0.', 'OBJETIVO: \u00c1ngulo de visi\u00f3n. OBJETIVO: Segmento vertical. 2,0 MP: 38,5\u00b0 - 1,1\u00b0. 4,0 MP: 42,8\u00b0 - 1,3\u00b0. 8,0 MP: 42,8\u00b0 - 1,3\u00b0.', 'OBJETIVO: Zoom. OBJETIVO: Zoom. 2,0 MP: 40x. 4,0 MP: 36x1. 8,0 MP: 36x1.']", "[MATERIAL] camara [MODELO] H5A PTZ Resistente [PROVEEDOR] Avigilon [TABLA] ['CONTROL DE IMAGEN: Compresi\u00f3n de video. 2,0 MP: H.264 HDSM SmartCodec, H.265 HDSM SmartCodec, Motion JPEG. 4,0 MP: H.264 HDSM SmartCodec, H.265 HDSM SmartCodec, Motion JPEG. 8 MP: H.264 HDSM SmartCodec, H.265 HDSM SmartCodec, Motion JPEG.', 'CONTROL DE IMAGEN: Transmisi\u00f3n. 2,0 MP: Transmisi\u00f3n m\u00faltiple H.264, Transmisi\u00f3n m\u00faltiple H.265, Motion JPEG. 4,0 MP: Transmisi\u00f3n m\u00faltiple H.264, Transmisi\u00f3n m\u00faltiple H.265, Motion JPEG. 8 MP: Transmisi\u00f3n m\u00faltiple H.264, Transmisi\u00f3n m\u00faltiple H.265, Motion JPEG.', 'CONTROL DE IMAGEN: Detecci\u00f3n de movimiento. 2,0 MP: Movimiento de p\u00edxeles: Umbral y sensibilidad seleccionables. Detecci\u00f3n de objetos clasificados. 4,0 MP: Movimiento de p\u00edxeles: Umbral y sensibilidad seleccionables. Detecci\u00f3n de objetos clasificados. 8 MP: Movimiento de p\u00edxeles: Umbral y sensibilidad seleccionables. Detecci\u00f3n de objetos clasificados.', 'CONTROL DE IMAGEN: Control electr\u00f3nico del obturador. 2,0 MP: Autom\u00e1tico, manual (de 1/1 a 1/10 000 s). 4,0 MP: Autom\u00e1tico, manual (de 1/1 a 1/10 000 s). 8 MP: Autom\u00e1tico, manual (de 1/1 a 1/10 000 s).', 'CONTROL DE IMAGEN: Control del diafragma. 2,0 MP: Autom\u00e1tico, abierto, cerrado. 4,0 MP: Autom\u00e1tico, abierto, cerrado. 8 MP: Autom\u00e1tico, abierto, cerrado.', 'CONTROL DE IMAGEN: Control de d\u00eda/noche. 2,0 MP: Autom\u00e1tico, manual. 4,0 MP: Autom\u00e1tico, manual. 8 MP: Autom\u00e1tico, manual.', 'CONTROL DE IMAGEN: Control de parpadeo. 2,0 MP: 60 Hz, 50 Hz. 4,0 MP: 60 Hz, 50 Hz. 8 MP: 60 Hz, 50 Hz.', 'CONTROL DE IMAGEN: Balance de blancos. 2,0 MP: Autom\u00e1tico, manual. 4,0 MP: Autom\u00e1tico, manual. 8 MP: Autom\u00e1tico, manual.', 'CONTROL DE IMAGEN: Compensaci\u00f3n de contraluz. 2,0 MP: Activar/Desactivar. 4,0 MP: Activar/Desactivar. 8 MP: Activar/Desactivar.', 'CONTROL DE IMAGEN: Zonas de privacidad. 2,0 MP: 3D, hasta 64 zonas. 4,0 MP: 3D, hasta 64 zonas. 8 MP: 3D, hasta 64 zonas.', 'CONTROL DE IMAGEN: Preselecciones. 2,0 MP: 500 preselecciones con nombre. 4,0 MP: 500 preselecciones con nombre. 8 MP: 500 preselecciones con nombre.', 'CONTROL DE IMAGEN: Rondas. 2,0 MP: 10 rondas con nombre. 4,0 MP: 10 rondas con nombre. 8 MP: 10 rondas con nombre.', 'CONTROL DE IMAGEN: Zoom digital. 2,0 MP: Hasta 100 aumentos cuando se utiliza con ACC\u2122Client. 4,0 MP: Hasta 100 aumentos cuando se utiliza con ACC\u2122Client. 8 MP: Hasta 100 aumentos cuando se utiliza con ACC\u2122Client.', 'CONTROL DE IMAGEN: Estabilizaci\u00f3n de la imagen electr\u00f3nica. 2,0 MP: No. 4,0 MP: S\u00ed. 8 MP: S\u00ed.', 'CONTROL DE IMAGEN: Desempa\u00f1ado digital. 2,0 MP: Ajustable/Desactivado. 4,0 MP: Ajustable/Desactivado. 8 MP: Ajustable/Desactivado.']", "[MATERIAL] camara [MODELO] H5A PTZ Resistente [PROVEEDOR] Avigilon [TABLA] ['RED: Red. RED: 100BASE-TX.', 'RED: Tipo de cableado. RED: Se requiere un cable Ethernet blindado (STP) CAT5e/CAT6 para cumplir en su totalidad con los est\u00e1ndares regulatorios de EMC.', 'RED: Conector. RED: RJ-45.', 'RED: ONVIF. RED: Conformidad con ONVIF Perfil S, Perfil T, y Perfil G (www.onvif.org).', 'RED: Seguridad. RED: Protecci\u00f3n por contrase\u00f1a, cifrado HTTPS, autenticaci\u00f3n impl\u00edcita, autenticaci\u00f3n WS, registro de acceso de usuario, autenticaci\u00f3n basada en el puerto 802.1x, FIPS 140-2 L1 (con licencia de c\u00e1mara opcional), FIPS 140-2 L3 (con licencia de c\u00e1mara opcional).', 'RED: Protocolos. RED: IPv6, IPv4, HTTP, HTTPS, SOAP, DNS, NTP, RTSP, RTCP, RTP, TCP, UDP, IGMPv2, ICMP, DHCP, Zeroconf, ARP, HSTS.', 'RED: Protocolos de transmisi\u00f3n. RED: RTP/UDP, RTP/UDP multidifusi\u00f3n, RTP/RTSP/TCP, RTP/RTSP/HTTP/TCP, RTP/RTSP/HTTPS/TCP, HTTP.', 'RED: Protocolos de administraci\u00f3n de dispositivos. RED: SNMP v2c, SNMP v3.']", "[MATERIAL] camara [MODELO] H5A PTZ Resistente [PROVEEDOR] Avigilon [TABLA] ['PERIF\u00c9RICOS: Entrada/Salida de audio. PERIF\u00c9RICOS: Ninguna.', 'PERIF\u00c9RICOS: Terminales de E/S externos. PERIF\u00c9RICOS: 2 entradas de alarma, 2 salidas de alarma.', 'PERIF\u00c9RICOS: Almacenamiento interno. PERIF\u00c9RICOS: Ranura para microSD/microSDHC/microSDXC: se requiere tarjeta de clase de velocidad de video. Se recomienda clase V10 o mejor.']", "[MATERIAL] camara [MODELO] H5A PTZ Resistente [PROVEEDOR] Avigilon [TABLA] ['MEC\u00c1NICAS: Dimensiones (\u00d8 x Al). MEC\u00c1NICAS: Dimensiones (\u00d8 x Al). MEC\u00c1NICAS: \u00d8240 mm \u00d7 406 mm; \u00d89,45\u201d \u00d7 16,0\u201d.', 'MEC\u00c1NICAS: Peso. MEC\u00c1NICAS: C\u00e1mara. MEC\u00c1NICAS: 7,1 kg (15,6 lb).', 'MEC\u00c1NICAS: Peso. MEC\u00c1NICAS: de 5 megap\u00edxeles con iluminador IR. MEC\u00c1NICAS: 7,4 kg (16,3 lb).', 'MEC\u00c1NICAS: Ventana de cristal. MEC\u00c1NICAS: Ventana de cristal. MEC\u00c1NICAS: Espesor de 6 mm (0,24\u201d).', 'MEC\u00c1NICAS: Cuerpo. MEC\u00c1NICAS: Cuerpo. MEC\u00c1NICAS: Aluminio y tecnopol\u00edmero.', 'MEC\u00c1NICAS: Carcasa. MEC\u00c1NICAS: Carcasa. MEC\u00c1NICAS: Montaje colgante y en pedestal.', 'MEC\u00c1NICAS: Finalizar. MEC\u00c1NICAS: Finalizar. MEC\u00c1NICAS: Pintado con epoxy-poli\u00e9ster en polvo, cercano a RAL9002.', 'MEC\u00c1NICAS: Barrido vertical. MEC\u00c1NICAS: Barrido vertical. MEC\u00c1NICAS: Derecho: -90\u00b0 a +90\u00b0; Invertido: -40\u00b0 a +90\u00b0 Hasta 250\u00b0/segundo.', 'MEC\u00c1NICAS: Barrido horizontal. MEC\u00c1NICAS: Barrido horizontal. MEC\u00c1NICAS: 360\u00b0, infinito, hasta 250\u00b0/segundo.']", "[MATERIAL] camara [MODELO] H5A PTZ Resistente [PROVEEDOR] Avigilon [TABLA] ['EL\u00c9CTRICAS: Consumo de energ\u00eda. EL\u00c9CTRICAS: Consumo de energ\u00eda. EL\u00c9CTRICAS: M\u00e1x. 71 W con suministro de alimentaci\u00f3n auxiliar de 24 VDC o 90 W PoE, 100 VA con alimentaci\u00f3n auxiliar de 24 VAC Calificaci\u00f3n UL conforme se especifica en la etiqueta del producto = 5A m\u00e1x.', 'EL\u00c9CTRICAS: Fuente de alimentaci\u00f3n. EL\u00c9CTRICAS: Fuente de alimentaci\u00f3n externa. EL\u00c9CTRICAS: 24 VDC \u00b110 %; o 24 VAC rms \u00b110 %, 50 o 60 Hz.', 'EL\u00c9CTRICAS: Fuente de alimentaci\u00f3n. EL\u00c9CTRICAS: PoE*. EL\u00c9CTRICAS: PoE de 90 W: Phihong POE90U-1BT6-A-RC (n\u00famero de pieza de Avigilon POE-INJ-BT-90W-NA).', 'EL\u00c9CTRICAS: Conector de alimentaci\u00f3n. EL\u00c9CTRICAS: Conector de alimentaci\u00f3n. EL\u00c9CTRICAS: Bloque de terminales de dos cables, 18 AWG a 13 AWG.', 'EL\u00c9CTRICAS: Bater\u00eda de reserva RTC. EL\u00c9CTRICAS: Bater\u00eda de reserva RTC. EL\u00c9CTRICAS: Ninguna.']", "[MATERIAL] camara [MODELO] H5A PTZ Resistente [PROVEEDOR] Avigilon [TABLA] ['MEDIOAMBIENTALES: Temperatura de funcionamiento. MEDIOAMBIENTALES: Operaci\u00f3n continua de -40 \u00b0C a +65 \u00b0C (-40 \u00b0F a 149 \u00b0F).', 'MEDIOAMBIENTALES: Temperatura de almacenamiento. MEDIOAMBIENTALES: De -40 \u00b0C a +70 \u00b0C (-40 \u00b0F a 158 \u00b0F).', 'MEDIOAMBIENTALES: Humedad. MEDIOAMBIENTALES: Del 5 % al 95 % sin condensaci\u00f3n.', 'MEDIOAMBIENTALES: Puesta en marcha en fr\u00edo. MEDIOAMBIENTALES: Retardo al inicio hasta 135 minutos a temperaturas inferiores a -10 \u00b0C (14 \u00b0F).', 'MEDIOAMBIENTALES: Resistencia al viento. MEDIOAMBIENTALES: sostenida de 230 km/h (143 mph).']", "[MATERIAL] camara [MODELO] H5A PTZ Resistente [PROVEEDOR] Avigilon [TABLA] ['CERTIFICACIONES: Certificaciones/Directivas. CERTIFICACIONES: UL, cUL, CE, UKCA, ROHS, RCM, NOM, KC, BIS.', 'CERTIFICACIONES: Seguridad. CERTIFICACIONES: UL 62368-1, CSA 62368-1, IEC/EN 62368-1, IEC/EN 62471.', 'CERTIFICACIONES: Medioambiente y rendimiento. CERTIFICACIONES: UL/CSA/IEC 60950-22, calificaci\u00f3n de impactos IEC 62262 IK10 (solo para la carcasa), IEC 60529 IP66, IP67, IP68 calificaci\u00f3n clim\u00e1tica, IEC 60068-2-1, IEC 60068-2-2, IEC 60068-2-6, IEC 60068-2-30, NEMA TS 2 para 2.2.7 - 2.2.9, Type 4X and 6P, roc\u00edo salino ASTM B117, ISO 14993, MIL-STD-810-H, MIL-STD-167-1A.', 'CERTIFICACIONES: Emisiones electromagn\u00e9ticas. CERTIFICACIONES: FCC Secci\u00f3n 15 Subsecci\u00f3n B Clase A, IC ICES-003 Clase A, EN 55032 Clase A, EN 61000-6-4, EN 61000-3-2, EN 61000-3-3, EN 50121-4.', 'CERTIFICACIONES: Inmunidad electromagn\u00e9tica. CERTIFICACIONES: EN 55035, EN 50130-4, EN 50121-4.', 'CERTIFICACIONES: Garant\u00eda. CERTIFICACIONES: Garant\u00eda limitada de 5 a\u00f1os. Garant\u00eda extendida no disponible.']", "[MATERIAL] camara [MODELO] H5A PTZ Resistente [PROVEEDOR] Avigilon [TABLA] ['ESPECIFICACIONES DEL AN\u00c1LISIS: EVENTOS DE AN\u00c1LISIS ADMITIDOS EN LA POSICI\u00d3N DE INICIO. ESPECIFICACIONES DEL AN\u00c1LISIS: EVENTOS DE AN\u00c1LISIS ADMITIDOS EN LA POSICI\u00d3N DE INICIO.', 'ESPECIFICACIONES DEL AN\u00c1LISIS: Objetos en el \u00e1rea de inter\u00e9s. ESPECIFICACIONES DEL AN\u00c1LISIS: El evento se activa cuando el tipo de objeto seleccionado se desplaza dentro de la regi\u00f3n de inter\u00e9s.', 'ESPECIFICACIONES DEL AN\u00c1LISIS: Objetos deambulantes. ESPECIFICACIONES DEL AN\u00c1LISIS: El evento se activa cuando el tipo de objeto seleccionado permanece dentro de la regi\u00f3n de inter\u00e9s durante un tiempo prolongado.', 'ESPECIFICACIONES DEL AN\u00c1LISIS: Objetos que cruzan un haz de luz. ESPECIFICACIONES DEL AN\u00c1LISIS: El evento se activa cuando una cantidad determinada de objetos cruza el haz direccional que se configura en el campo de visi\u00f3n de la c\u00e1mara. El haz puede ser unidireccional o bidireccional.', 'ESPECIFICACIONES DEL AN\u00c1LISIS: El objeto aparece o entra en el \u00e1rea. ESPECIFICACIONES DEL AN\u00c1LISIS: El evento se activa cada vez que un objeto entra en la regi\u00f3n de inter\u00e9s. Este evento se puede utilizar para contar objetos.', 'ESPECIFICACIONES DEL AN\u00c1LISIS: Objeto no presente en el \u00e1rea. ESPECIFICACIONES DEL AN\u00c1LISIS: El evento se activa cuando no hay objetos presentes en la regi\u00f3n de inter\u00e9s.', 'ESPECIFICACIONES DEL AN\u00c1LISIS: Objetos que entran en el \u00e1rea. ESPECIFICACIONES DEL AN\u00c1LISIS: El evento se activa cuando el n\u00famero de objetos especificado ha entrado en la regi\u00f3n de inter\u00e9s.', 'ESPECIFICACIONES DEL AN\u00c1LISIS: Objetos que abandonan el \u00e1rea. ESPECIFICACIONES DEL AN\u00c1LISIS: El evento se activa cuando el n\u00famero de objetos especificado ha abandonado la regi\u00f3n de inter\u00e9s.', 'ESPECIFICACIONES DEL AN\u00c1LISIS: El objeto se detiene en el \u00e1rea. ESPECIFICACIONES DEL AN\u00c1LISIS: El evento se activa cuando un objeto se mueve en una regi\u00f3n de inter\u00e9s y luego se detiene durante un periodo de tiempo determinado.', 'ESPECIFICACIONES DEL AN\u00c1LISIS: Direcci\u00f3n prohibida. ESPECIFICACIONES DEL AN\u00c1LISIS: El evento se activa cuando un objeto se mueve en la direcci\u00f3n prohibida del recorrido.', 'ESPECIFICACIONES DEL AN\u00c1LISIS: Detecci\u00f3n de alteraci\u00f3n. ESPECIFICACIONES DEL AN\u00c1LISIS: El evento se activa cuando la escena cambia de manera inesperada.']", "[MATERIAL] camara [MODELO] H5A PTZ Resistente [PROVEEDOR] Avigilon [TABLA] ['SEGUIMIENTO AUTOM\u00c1TICO DE OBJETOS EN EL \u00c1REA DE INTER\u00c9S: Seguimiento autom\u00e1tico de objetos en el \u00e1rea de inter\u00e9s. SEGUIMIENTO AUTOM\u00c1TICO DE OBJETOS EN EL \u00c1REA DE INTER\u00c9S: El evento se activa cuando el tipo de objeto seleccionado se desplaza dentro de la regi\u00f3n de inter\u00e9s definida en la posici\u00f3n de inicio. La c\u00e1mara se reposicionar\u00e1 autom\u00e1ticamente para seguir el objeto y volver\u00e1 a la posici\u00f3n de inicio preestablecida una vez que ya no detecte el objeto.']", "[MATERIAL] camara [MODELO] H5A PTZ Resistente [PROVEEDOR] Avigilon [TABLA] ['TIPOS DE OBJETOS CLASIFICADOS ADMITIDOS: Tipos de objetos en modo exterior. TIPOS DE OBJETOS CLASIFICADOS ADMITIDOS: Veh\u00edculo, subtipos: Coche, cami\u00f3n, bicicleta, motocicleta, autob\u00fas Persona.', 'TIPOS DE OBJETOS CLASIFICADOS ADMITIDOS: Tipos de objetos en modo interior. TIPOS DE OBJETOS CLASIFICADOS ADMITIDOS: Persona.']", "[MATERIAL] camara [MODELO] H5A PTZ Resistente [PROVEEDOR] Avigilon [TABLA] ['ENSE\u00d1AR CON EL EJEMPLO: Ense\u00f1ar con el ejemplo. ENSE\u00d1AR CON EL EJEMPLO: S\u00ed, cuando se utiliza con Avigilon Control Center\u2122.']", "[MATERIAL] camara [MODELO] H5A PTZ Resistente [PROVEEDOR] Avigilon [TABLA] ['FUNCIONES COMPATIBLES CON VERSIONES DE AVIGILON CONTROL CENTER (ACC): ACC Versi\u00f3n 6.14.12 o superior*. FUNCIONES COMPATIBLES CON VERSIONES DE AVIGILON CONTROL CENTER (ACC): Todos los eventos anal\u00edticos compatibles con dos tipos de objetos clasificados: persona o veh\u00edculo. B\u00fasqueda de apariencia al combinar con el hardware de servidor adecuado. No es compatible con el seguimiento autom\u00e1tico. Compatible con H.265.', 'FUNCIONES COMPATIBLES CON VERSIONES DE AVIGILON CONTROL CENTER (ACC): ACC Versi\u00f3n 7.14.0 o superior**. FUNCIONES COMPATIBLES CON VERSIONES DE AVIGILON CONTROL CENTER (ACC): Todos los eventos anal\u00edticos compatibles con personas y veh\u00edculos y todos los subtipos de veh\u00edculos como objetos clasificados. B\u00fasqueda de apariencia al combinar con el hardware de servidor adecuado. Compatible con H.265.']", "[MATERIAL] camara [MODELO] H5A PTZ Resistente [PROVEEDOR] Avigilon [TABLA] ['[X.X]: X. PULGADAS: MM.']", "[MATERIAL] camara [MODELO] H5A PTZ Resistente [PROVEEDOR] Avigilon [TABLA] ['C\u00c1MARAS PTZ: C\u00c1MARAS PTZ. C\u00c1MARAS PTZ: MP. C\u00c1MARAS PTZ: WDR. C\u00c1MARAS PTZ: TECNOLOG\u00cdA LIGHTCATCHER. C\u00c1MARAS PTZ: AN\u00c1LISIS EN LA POSICI\u00d3N DE INICIO. C\u00c1MARAS PTZ: OBJETIVO. C\u00c1MARAS PTZ: ZOOM. C\u00c1MARAS PTZ: IP66/67/68. C\u00c1MARAS PTZ: HDSM SMARTCODEC.', 'C\u00c1MARAS PTZ: 2.0C-H5A-RGDPTZ-DP36- B. C\u00c1MARAS PTZ: 2.0. C\u00c1MARAS PTZ: \u2713. C\u00c1MARAS PTZ: \u2713. C\u00c1MARAS PTZ: \u2713 4. C\u00c1MARAS PTZ: ,25 - 170 mm. C\u00c1MARAS PTZ: 40x*. C\u00c1MARAS PTZ: \u2713. C\u00c1MARAS PTZ: \u2713.', 'C\u00c1MARAS PTZ: 4.0C-H5A-RGDPTZ-DP36. C\u00c1MARAS PTZ: 4,0. C\u00c1MARAS PTZ: \u2713. C\u00c1MARAS PTZ: \u2713. C\u00c1MARAS PTZ: \u2713. C\u00c1MARAS PTZ: 4,4 - 88 mm. C\u00c1MARAS PTZ: 36x*. C\u00c1MARAS PTZ: \u2713. C\u00c1MARAS PTZ: \u2713.', 'C\u00c1MARAS PTZ: 8.0C-H5A-RGDPTZ-DP36. C\u00c1MARAS PTZ: 8,0. C\u00c1MARAS PTZ: \u2713. C\u00c1MARAS PTZ: \u2713. C\u00c1MARAS PTZ: \u2713. C\u00c1MARAS PTZ: 4,4 - 88 mm. C\u00c1MARAS PTZ: 36x*. C\u00c1MARAS PTZ: \u2713. C\u00c1MARAS PTZ: \u2713.']", "[MATERIAL] camara [MODELO] H5A PTZ Resistente [PROVEEDOR] Avigilon [TABLA] ['ACCESORIOS: POE-INJ-BT-90W-NA. DESCRIPCI\u00d3N: Inyector PoE Gigabit 802.3bt de 90 W, puerto \u00fanico.', 'ACCESORIOS: AVUEI8AA. DESCRIPCI\u00d3N: Iluminador IR, 850 nm, compatible con H5A Rugged PTZ, cercano a RAL9002.', 'ACCESORIOS: AVUEI8AAP. DESCRIPCI\u00d3N: Iluminador IR de larga distancia, 850 nm, compatible con H5A Rugged PTZ, cercano a RAL9002.', 'ACCESORIOS: AVUEI9AA. DESCRIPCI\u00d3N: Iluminador IR, 940 nm, compatible con H5A Rugged PTZ, cercano a RAL9002.', 'ACCESORIOS: AVUEIWAA. DESCRIPCI\u00d3N: Iluminador de luz blanca, compatible con H5A Rugged PTZ, cercano a RAL9002.', 'ACCESORIOS: AVUEIWAAP. DESCRIPCI\u00d3N: Iluminador de luz blanca de larga distancia, compatible con H5A Rugged PTZ, cercano a RAL9002.', 'ACCESORIOS: AVUEBWAA. DESCRIPCI\u00d3N: Montaje de brazo de pared, compatible con H5A Rugged PTZ, cercano a RAL9002.', 'ACCESORIOS: AVUEBP0AA. DESCRIPCI\u00d3N: Soporte de montaje parapetado, canal de cable interno, compatible con H5A Rugged PTZ, cercano a RAL9002.', 'ACCESORIOS: AVUEBP4AA. DESCRIPCI\u00d3N: Soporte de montaje parapetado con conectores r\u00e1pidos, RJ45 (Ethernet y PoE) y 4 polos con terminal atornillada (alimentaci\u00f3n y E/S), compatible con H5A Rugged PTZ, cercano a RAL9002.', 'ACCESORIOS: AVUEBP7AA. DESCRIPCI\u00d3N: Soporte de montaje parapetado con conectores r\u00e1pidos, RJ45 (Ethernet y PoE) y 7 polos con soldadura (alimentaci\u00f3n y E/S), compatible con H5A Rugged PTZ, cercano a RAL9002.']", "[MATERIAL] camara [MODELO] H5A PTZ Resistente [PROVEEDOR] Avigilon [TABLA] ['ACCESORIOS: AVUEAP. DESCRIPCI\u00d3N: Adaptador de montaje en poste, acero inoxidable AISI 316L, compatible con montaje con brazo para pared AVUEBWAA.', 'ACCESORIOS: AVUEAC. DESCRIPCI\u00d3N: Adaptador de montaje en esquina, acero inoxidable AISI 316L, compatible con montaje con brazo para pared AVUEBWAA.', 'ACCESORIOS: AVUEAW. DESCRIPCI\u00d3N: Adaptador de montaje en placa parapetada, acero inoxidable AISI 316L, compatible con montaje con soportes de montaje parapetados.', 'ACCESORIOS: AVWASPT0V5L5M00. DESCRIPCI\u00d3N: Bomba con arandela, tanque de agua de 5 L, bombea hasta 5 m (16,4 pies), entrada de 230VAC/24VAC/120VAC, compatible con H5A Rugged PTZ.', 'ACCESORIOS: AVWASPT0V23L11M00. DESCRIPCI\u00d3N: Bomba con arandela, tanque de agua de 23 L, bombea hasta 11 m (36 pies), entrada de 230VAC/24VAC/120VAC, compatible con H5A Rugged PTZ.', 'ACCESORIOS: AVWASPT1V23L30M00. DESCRIPCI\u00d3N: Bomba con arandela, tanque de agua de 23 L, bombea hasta 30 m (98 pies), entrada de 230VAC, compatible con H5A Rugged PTZ.', 'ACCESORIOS: AVWASPT3V23L30M00. DESCRIPCI\u00d3N: Bomba con arandela, tanque de agua de 23 L, bombea hasta 30 m (98 pies), entrada de 120VAC, compatible con H5A Rugged PTZ.', 'ACCESORIOS: AVCOMB100A. DESCRIPCI\u00d3N: Caja de comunicaci\u00f3n con fuente de alimentaci\u00f3n e interruptor, 220 a 230 VAC, policarbonato, compatible con H5A Rugged PTZ.', 'ACCESORIOS: AVCOMB200A. DESCRIPCI\u00d3N: Caja de comunicaci\u00f3n con fuente de alimentaci\u00f3n e interruptor, 24 VAC, policarbonato, compatible con H5A Rugged PTZ.', 'ACCESORIOS: AVCOMB300A. DESCRIPCI\u00d3N: Caja de comunicaci\u00f3n con fuente de alimentaci\u00f3n e interruptor, 120 a 127 VAC, policarbonato, compatible con H5A Rugged PTZ.', 'ACCESORIOS: AVSURGEPR. DESCRIPCI\u00d3N: Protector frente a subidas de tensi\u00f3n de la l\u00ednea Ethernet.', 'ACCESORIOS: AVOUEWIPER. DESCRIPCI\u00d3N: Blade de escobilla de repuesto.', 'ACCESORIOS: AVOUEMAN. DESCRIPCI\u00d3N: Kit de mantenimiento de la c\u00e1mara (incluye 1 conector de alimentaci\u00f3n, 1 conector de E/S, 1 placa de acople de cadena de seguridad, 2 prensaestopas de cable M16, 1 prensaestopas de cable M20, 1 junta de reducci\u00f3n para prensaestopas de cable M20, 1 junta de reducci\u00f3n para prensaestopas de cable M16, 1 junta de base, 1 llave Allen, 1 fusible de 2,5 A).']", "[MATERIAL] camara [MODELO] H5A PTZ Resistente [PROVEEDOR] Avigilon [TABLA] ['CAM-FIPS: CAM-FIPS-CRYPTR-L3. Licencia de c\u00e1mara para habilitar el modo criptogr\u00e1fico FIPS Nivel 1 en cualquier c\u00e1mara H5A: MSI CRYPTR SD con licencia de c\u00e1mara para habilitar el modo criptogr\u00e1fico FIPS Nivel 3 en cualquier c\u00e1mara H5A1.']"], "resumenes": ["[TABLA] Modelo H5A PTZ Resistente de Avigilon: El modelo de 2,0 MP utiliza un sensor CMOS de barrido progresivo de 1/2,8\" con una resoluci\u00f3n de 1937 (H) \u00d7 1097 (V) y un \u00e1rea de digitalizaci\u00f3n de 4,8 mm (H) \u00d7 2,7 mm (V) o 0,189\" (H) \u00d7 0,106\" (V). La distancia m\u00e1xima de iluminaci\u00f3n IR var\u00eda entre 75 m (246 pies) y 200 m (656 pies), dependiendo del tipo de AVUEI. La iluminaci\u00f3n m\u00ednima es de 0,03 lux (F/1,6) en modo color y 0,02 lux (F/1,6) en modo monocromo. Tiene un rango din\u00e1mico de m\u00e1s de 120 dB y puede alcanzar hasta 60 fps. La relaci\u00f3n de aspecto soporta hasta (16:9) 384\u00d7216 o (5:4) 320\u00d7256 y cuenta con filtro de reducci\u00f3n de ruido 3D. El modelo de 4,0 MP est\u00e1 equipado con un sensor CMOS tipo \"Exmor R\" de 1/2,5\" y una resoluci\u00f3n de 2688 (H) \u00d7 1512 (V) con un \u00e1rea de digitalizaci\u00f3n de 6,22 mm (H) \u00d7 3,50 mm (V) o 0,245\" (H) \u00d7 0,137\" (V). La distancia m\u00e1xima de iluminaci\u00f3n IR oscila entre 20 m (66 pies) y 100 m (328 pies), dependiendo del tipo de AVUEI. La iluminaci\u00f3n m\u00ednima es de 0,3 lux (F/2,0) en modo color y 0,09 lux (F/2,0) en modo monocromo. Posee un rango din\u00e1mico de 100 dB y puede alcanzar hasta 30 fps. La relaci\u00f3n de aspecto soporta hasta (16:9) 384\u00d7216 o (5:4) 320\u00d7256 y tambi\u00e9n incluye filtro de reducci\u00f3n de ruido 3D. El modelo de 8,0 MP utiliza un sensor CMOS tipo \"Exmor R\" de 1/2,5\" con una resoluci\u00f3n de 3840 (H) \u00d7 2160 (V) y un \u00e1rea de digitalizaci\u00f3n de 6,22 mm (H) \u00d7 3,50 mm (V) o 0,245\" (H) \u00d7 0,137\" (V). La distancia m\u00e1xima de iluminaci\u00f3n IR var\u00eda entre 20 m (66 pies) y 100 m (328 pies), dependiendo del tipo de AVUEI. La iluminaci\u00f3n m\u00ednima es de 0,3 lux (F/2,0) en modo color y 0,09 lux (F/2,0) en modo monocromo. Tiene un rango din\u00e1mico de 100 dB y puede alcanzar hasta 30 fps. La relaci\u00f3n de aspecto soporta hasta (16:9) 384\u00d7216 o (5:4) 320\u00d7256 y cuenta con filtro de reducci\u00f3n de ruido 3D.", "[TABLA] El modelo H5A PTZ Resistente de Avigilon tiene las siguientes especificaciones t\u00e9cnicas: Para la c\u00e1mara de 2,0 MP: El objetivo tiene un rango de 4,25 a 170 mm con una apertura de F/1,6 a F/4,95 y enfoque autom\u00e1tico. El \u00e1ngulo de visi\u00f3n horizontal es de 66,35\u00b0 a 1,9\u00b0 y el \u00e1ngulo de visi\u00f3n vertical es de 38,5\u00b0 a 1,1\u00b0. El zoom es de 40x. Para la c\u00e1mara de 4,0 MP: El objetivo tiene un rango de 4,4 a 88 mm con una apertura de F/2,0 a F/3,8 y enfoque autom\u00e1tico. El \u00e1ngulo de visi\u00f3n horizontal es de 69,7\u00b0 a 2,2\u00b0 y el \u00e1ngulo de visi\u00f3n vertical es de 42,8\u00b0 a 1,3\u00b0. El zoom es de 36x. Para la c\u00e1mara de 8,0 MP: El objetivo tiene un rango de 4,4 a 88 mm con una apertura de F/2,0 a F/3,8 y enfoque autom\u00e1tico. El \u00e1ngulo de visi\u00f3n horizontal es de 69,7\u00b0 a 2,2\u00b0 y el \u00e1ngulo de visi\u00f3n vertical es de 42,8\u00b0 a 1,3\u00b0. El zoom es de 36x.", "[TABLA] Modelo H5A PTZ Resistente de Avigilon: Para el modelo de 2,0 MP, la compresi\u00f3n de video es H.264 HDSM SmartCodec, H.265 HDSM SmartCodec y Motion JPEG. La transmisi\u00f3n incluye H.264, H.265 y Motion JPEG. La detecci\u00f3n de movimiento se realiza mediante el movimiento de p\u00edxeles con umbral y sensibilidad seleccionables, adem\u00e1s de la detecci\u00f3n de objetos clasificados. El control electr\u00f3nico del obturador puede ser autom\u00e1tico o manual (de 1/1 a 1/10 000 s). El control del diafragma es autom\u00e1tico, abierto o cerrado. El control de d\u00eda/noche es autom\u00e1tico o manual. El control de parpadeo se ajusta a 60 Hz o 50 Hz. El balance de blancos puede ser autom\u00e1tico o manual. La compensaci\u00f3n de contraluz se puede activar o desactivar. Se pueden configurar hasta 64 zonas de privacidad en 3D. Se permiten 500 preselecciones con nombre y 10 rondas con nombre. El zoom digital llega hasta 100 aumentos con ACC\u2122Client. No tiene estabilizaci\u00f3n de imagen electr\u00f3nica, y el desempa\u00f1ado digital es ajustable o desactivado. Para el modelo de 4,0 MP, la compresi\u00f3n de video es H.264 HDSM SmartCodec, H.265 HDSM SmartCodec y Motion JPEG. La transmisi\u00f3n incluye H.264, H.265 y Motion JPEG. La detecci\u00f3n de movimiento se realiza mediante el movimiento de p\u00edxeles con umbral y sensibilidad seleccionables, adem\u00e1s de la detecci\u00f3n de objetos clasificados. El control electr\u00f3nico del obturador puede ser autom\u00e1tico o manual (de 1/1 a 1/10 000 s). El control del diafragma es autom\u00e1tico, abierto o cerrado. El control de d\u00eda/noche es autom\u00e1tico o manual. El control de parpadeo se ajusta a 60 Hz o 50 Hz. El balance de blancos puede ser autom\u00e1tico o manual. La compensaci\u00f3n de contraluz se puede activar o desactivar. Se pueden configurar hasta 64 zonas de privacidad en 3D. Se permiten 500 preselecciones con nombre y 10 rondas con nombre. El zoom digital llega hasta 100 aumentos con ACC\u2122Client. Tiene estabilizaci\u00f3n de imagen electr\u00f3nica y el desempa\u00f1ado digital es ajustable o desactivado. Para el modelo de 8,0 MP, la compresi\u00f3n de video es H.264 HDSM SmartCodec, H.265 HDSM SmartCodec y Motion JPEG. La transmisi\u00f3n incluye H.264, H.265 y Motion JPEG. La detecci\u00f3n de movimiento se realiza mediante el movimiento de p\u00edxeles con umbral y sensibilidad seleccionables, adem\u00e1s de la detecci\u00f3n de objetos clasificados. El control electr\u00f3nico del obturador puede ser autom\u00e1tico o manual (de 1/1 a 1/10 000 s). El control del diafragma es autom\u00e1tico, abierto o cerrado. El control de d\u00eda/noche es autom\u00e1tico o manual. El control de parpadeo se ajusta a 60 Hz o 50 Hz. El balance de blancos puede ser autom\u00e1tico o manual. La compensaci\u00f3n de contraluz se puede activar o desactivar. Se pueden configurar hasta 64 zonas de privacidad en 3D. Se permiten 500 preselecciones con nombre y 10 rondas con nombre. El zoom digital llega hasta 100 aumentos con ACC\u2122Client. Tiene estabilizaci\u00f3n de imagen electr\u00f3nica y el desempa\u00f1ado digital es ajustable o desactivado.", "[TABLA] El modelo H5A PTZ Resistente de Avigilon es una c\u00e1mara que cuenta con conectividad de red 100BASE-TX y requiere un cable Ethernet blindado (STP) CAT5e/CAT6 para cumplir con los est\u00e1ndares regulatorios de EMC. Utiliza un conector RJ-45 y es compatible con ONVIF Perfil S, Perfil T, y Perfil G. En t\u00e9rminos de seguridad, ofrece protecci\u00f3n por contrase\u00f1a, cifrado HTTPS, autenticaci\u00f3n impl\u00edcita, autenticaci\u00f3n WS, registro de acceso de usuario, autenticaci\u00f3n basada en el puerto 802.1x, y puede cumplir con FIPS 140-2 L1 y L3 con licencias de c\u00e1mara opcionales. Los protocolos soportados incluyen IPv6, IPv4, HTTP, HTTPS, SOAP, DNS, NTP, RTSP, RTCP, RTP, TCP, UDP, IGMPv2, ICMP, DHCP, Zeroconf, ARP, y HSTS. Para la transmisi\u00f3n, soporta RTP/UDP, RTP/UDP multidifusi\u00f3n, RTP/RTSP/TCP, RTP/RTSP/HTTP/TCP, RTP/RTSP/HTTPS/TCP, y HTTP. Adem\u00e1s, utiliza SNMP v2c y SNMP v3 para la administraci\u00f3n de dispositivos.", "[TABLA] El modelo H5A PTZ Resistente de Avigilon tiene las siguientes especificaciones t\u00e9cnicas: incluye entrada/salida de audio, terminales de E/S externos con 2 entradas de alarma y 2 salidas de alarma. Adem\u00e1s, cuenta con almacenamiento interno mediante una ranura para tarjetas microSD/microSDHC/microSDXC, requiriendo una tarjeta de clase de velocidad de video, siendo recomendada la clase V10 o mejor.", "[TABLA] El modelo H5A PTZ Resistente de Avigilon tiene las siguientes especificaciones t\u00e9cnicas: Dimensiones mec\u00e1nicas de \u00d8240 mm \u00d7 406 mm (\u00d89,45\u201d \u00d7 16,0\u201d). El peso de la c\u00e1mara es de 7,1 kg (15,6 lb), y con un iluminador IR de 5 megap\u00edxeles, el peso es de 7,4 kg (16,3 lb). La ventana de cristal tiene un espesor de 6 mm (0,24\u201d). El cuerpo est\u00e1 hecho de aluminio y tecnopol\u00edmero. La carcasa permite montaje colgante y en pedestal. El acabado es pintado con epoxy-poli\u00e9ster en polvo, cercano a RAL9002. El barrido vertical es de -90\u00b0 a +90\u00b0 en posici\u00f3n derecha y de -40\u00b0 a +90\u00b0 en posici\u00f3n invertida, con una velocidad de hasta 250\u00b0/segundo. El barrido horizontal es de 360\u00b0 infinito, con una velocidad de hasta 250\u00b0/segundo.", "[TABLA] El modelo H5A PTZ Resistente de Avigilon presenta las siguientes especificaciones t\u00e9cnicas: Consumo de energ\u00eda m\u00e1ximo de 71 W con suministro de alimentaci\u00f3n auxiliar de 24 VDC o 90 W PoE, alcanzando 100 VA con alimentaci\u00f3n auxiliar de 24 VAC. La calificaci\u00f3n UL seg\u00fan la etiqueta del producto es de 5A m\u00e1x. La fuente de alimentaci\u00f3n externa puede ser de 24 VDC \u00b110 % o 24 VAC rms \u00b110 %, 50 o 60 Hz. Tambi\u00e9n es compatible con PoE de 90 W, espec\u00edficamente con el Phihong POE90U-1BT6-A-RC (n\u00famero de pieza de Avigilon POE-INJ-BT-90W-NA). El conector de alimentaci\u00f3n es un bloque de terminales de dos cables, compatible con calibres de 18 AWG a 13 AWG. No cuenta con una bater\u00eda de reserva RTC.", "[TABLA] La c\u00e1mara modelo H5A PTZ Resistente de Avigilon tiene las siguientes especificaciones t\u00e9cnicas: La temperatura de funcionamiento en operaci\u00f3n continua var\u00eda de -40 \u00b0C a +65 \u00b0C (-40 \u00b0F a 149 \u00b0F). La temperatura de almacenamiento va de -40 \u00b0C a +70 \u00b0C (-40 \u00b0F a 158 \u00b0F). La humedad soportada es del 5 % al 95 % sin condensaci\u00f3n. La puesta en marcha en fr\u00edo puede tener un retardo al inicio de hasta 135 minutos a temperaturas inferiores a -10 \u00b0C (14 \u00b0F). Resiste vientos sostenidos de hasta 230 km/h (143 mph).", "[TABLA] El modelo H5A PTZ Resistente de Avigilon cuenta con varias certificaciones y directivas, incluyendo UL, cUL, CE, UKCA, ROHS, RCM, NOM, KC, y BIS. En t\u00e9rminos de seguridad, est\u00e1 certificado bajo UL 62368-1, CSA 62368-1, IEC/EN 62368-1, y IEC/EN 62471. En cuanto a medioambiente y rendimiento, cumple con UL/CSA/IEC 60950-22, tiene una calificaci\u00f3n de impactos IEC 62262 IK10 para la carcasa, y cumple con IEC 60529 IP66, IP67, IP68 para calificaci\u00f3n clim\u00e1tica, adem\u00e1s de IEC 60068-2-1, IEC 60068-2-2, IEC 60068-2-6, IEC 60068-2-30, NEMA TS 2 para 2.2.7 [LISTA] 2.2.9, Type 4X y 6P, roc\u00edo salino ASTM B117, ISO 14993, MIL-STD-810-H, y MIL-STD-167-1A. En emisiones electromagn\u00e9ticas, est\u00e1 certificada por FCC Secci\u00f3n 15 Subsecci\u00f3n B Clase A, IC ICES-003 Clase A, EN 55032 Clase A, EN 61000-6-4, EN 61000-3-2, EN 61000-3-3, y EN 50121-4. Respecto a inmunidad electromagn\u00e9tica, cumple con EN 55035, EN 50130-4, y EN 50121-4. Adem\u00e1s, tiene una garant\u00eda limitada de 5 a\u00f1os sin opci\u00f3n a garant\u00eda extendida.", "[TABLA] El modelo H5A PTZ Resistente de Avigilon cuenta con varias especificaciones t\u00e9cnicas en el an\u00e1lisis de eventos. Los eventos de an\u00e1lisis admitidos en la posici\u00f3n de inicio incluyen: detecci\u00f3n de objetos en el \u00e1rea de inter\u00e9s, activ\u00e1ndose cuando el tipo de objeto seleccionado se desplaza dentro de la regi\u00f3n de inter\u00e9s; detecci\u00f3n de objetos deambulantes, activ\u00e1ndose cuando el tipo de objeto seleccionado permanece dentro de la regi\u00f3n de inter\u00e9s durante un tiempo prolongado; detecci\u00f3n de objetos que cruzan un haz de luz, activ\u00e1ndose cuando una cantidad determinada de objetos cruza el haz direccional que se configura en el campo de visi\u00f3n de la c\u00e1mara, siendo el haz unidireccional o bidireccional; detecci\u00f3n de objetos que aparecen o entran en el \u00e1rea, activ\u00e1ndose cada vez que un objeto entra en la regi\u00f3n de inter\u00e9s, pudiendo utilizarse este evento para contar objetos; detecci\u00f3n de objeto no presente en el \u00e1rea, activ\u00e1ndose cuando no hay objetos presentes en la regi\u00f3n de inter\u00e9s; detecci\u00f3n de objetos que entran en el \u00e1rea, activ\u00e1ndose cuando el n\u00famero de objetos especificado ha entrado en la regi\u00f3n de inter\u00e9s; detecci\u00f3n de objetos que abandonan el \u00e1rea, activ\u00e1ndose cuando el n\u00famero de objetos especificado ha abandonado la regi\u00f3n de inter\u00e9s; detecci\u00f3n de objeto que se detiene en el \u00e1rea, activ\u00e1ndose cuando un objeto se mueve en una regi\u00f3n de inter\u00e9s y luego se detiene durante un periodo de tiempo determinado; detecci\u00f3n de direcci\u00f3n prohibida, activ\u00e1ndose cuando un objeto se mueve en la direcci\u00f3n prohibida del recorrido; y detecci\u00f3n de alteraci\u00f3n, activ\u00e1ndose cuando la escena cambia de manera inesperada.", "[TABLA] El modelo H5A PTZ Resistente de Avigilon cuenta con seguimiento autom\u00e1tico de objetos en el \u00e1rea de inter\u00e9s. Este evento se activa cuando el tipo de objeto seleccionado se desplaza dentro de la regi\u00f3n de inter\u00e9s definida en la posici\u00f3n de inicio. La c\u00e1mara se reposiciona autom\u00e1ticamente para seguir el objeto y vuelve a la posici\u00f3n de inicio preestablecida una vez que ya no detecta el objeto.", "[TABLA] El modelo H5A PTZ Resistente de Avigilon es una c\u00e1mara que admite la clasificaci\u00f3n de objetos en modo exterior para los tipos de objetos veh\u00edculo, con subtipos coche, cami\u00f3n, bicicleta, motocicleta y autob\u00fas, as\u00ed como persona. En modo interior, admite la clasificaci\u00f3n de objetos para persona.", "[TABLA] La c\u00e1mara H5A PTZ Resistente de Avigilon est\u00e1 dise\u00f1ada para ofrecer un rendimiento superior en condiciones exigentes. Este modelo se integra con el Avigilon Control Center\u2122 para proporcionar un control y monitoreo efectivos.", "[TABLA] El modelo H5A PTZ Resistente de Avigilon es una c\u00e1mara compatible con el Avigilon Control Center (ACC) versi\u00f3n 6.14.12 o superior, permitiendo todos los eventos anal\u00edticos compatibles con dos tipos de objetos clasificados: persona o veh\u00edculo. Tambi\u00e9n admite la b\u00fasqueda de apariencia al combinar con el hardware de servidor adecuado y es compatible con H.265. No es compatible con el seguimiento autom\u00e1tico. Con la versi\u00f3n ACC 7.14.0 o superior, esta c\u00e1mara admite todos los eventos anal\u00edticos para personas y veh\u00edculos, incluyendo todos los subtipos de veh\u00edculos como objetos clasificados, y sigue siendo compatible con la b\u00fasqueda de apariencia y H.265.", "[TABLA] El modelo H5A PTZ Resistente de Avigilon es una c\u00e1mara con caracter\u00edsticas t\u00e9cnicas avanzadas. La c\u00e1mara est\u00e1 dise\u00f1ada para ser duradera y resistente a condiciones adversas. Incluye un sensor de imagen de alta resoluci\u00f3n, capacidad de zoom \u00f3ptico, y movimiento PTZ (Pan-Tilt-Zoom) para una cobertura completa del \u00e1rea de vigilancia. Adem\u00e1s, est\u00e1 equipada con tecnolog\u00eda de an\u00e1lisis de video avanzado para detectar y responder a eventos en tiempo real. La carcasa es robusta y resistente al agua y al polvo, cumpliendo con los est\u00e1ndares IP66 e IK10, lo que garantiza su funcionamiento en entornos dif\u00edciles. La c\u00e1mara tambi\u00e9n ofrece opciones de almacenamiento local y remoto, as\u00ed como conectividad a trav\u00e9s de m\u00faltiples interfaces de red.", "[TABLA] Modelo H5A PTZ Resistente de Avigilon: Para el modelo 2.0C-H5A-RGDPTZ-DP36-B, cuenta con una resoluci\u00f3n de 2.0 MP, tecnolog\u00eda WDR y LightCatcher, an\u00e1lisis en la posici\u00f3n de inicio, un objetivo de 4,25 [LISTA] 170 mm y zoom de 40x. Est\u00e1 clasificada con IP66/67/68 y utiliza HDSM SmartCodec. Para el modelo 4.0C-H5A-RGDPTZ-DP36, tiene una resoluci\u00f3n de 4.0 MP, tecnolog\u00eda WDR y LightCatcher, an\u00e1lisis en la posici\u00f3n de inicio, un objetivo de 4,4 [LISTA] 88 mm y zoom de 36x. Tambi\u00e9n est\u00e1 clasificada con IP66/67/68 y utiliza HDSM SmartCodec. Para el modelo 8.0C-H5A-RGDPTZ-DP36, dispone de una resoluci\u00f3n de 8.0 MP, tecnolog\u00eda WDR y LightCatcher, an\u00e1lisis en la posici\u00f3n de inicio, un objetivo de 4,4 [LISTA] 88 mm y zoom de 36x. Al igual que los otros modelos, est\u00e1 clasificada con IP66/67/68 y utiliza HDSM SmartCodec.", "[TABLA] El modelo H5A PTZ Resistente de Avigilon es una c\u00e1mara equipada con varios accesorios. El inyector PoE Gigabit 802.3bt de 90 W (POE-INJ-BT-90W-NA) proporciona alimentaci\u00f3n a trav\u00e9s de un \u00fanico puerto. El iluminador IR de 850 nm (AVUEI8AA) y el de larga distancia (AVUEI8AAP) son compatibles con esta c\u00e1mara, al igual que el iluminador IR de 940 nm (AVUEI9AA). Tambi\u00e9n se dispone de un iluminador de luz blanca (AVUEIWAA) y uno de larga distancia (AVUEIWAAP). Para el montaje, se ofrecen un montaje de brazo de pared (AVUEBWAA) y varios soportes de montaje parapetado: uno con canal de cable interno (AVUEBP0AA), otro con conectores r\u00e1pidos RJ45 y 4 polos con terminal atornillada (AVUEBP4AA), y uno con conectores r\u00e1pidos RJ45 y 7 polos con soldadura (AVUEBP7AA). Todos los accesorios son compatibles y cercanos al color RAL9002.", "[TABLA] La c\u00e1mara H5A PTZ Resistente de Avigilon es un dispositivo avanzado que ofrece varias opciones de montaje y accesorios adicionales. Los adaptadores de montaje est\u00e1n hechos de acero inoxidable AISI 316L y son compatibles con el montaje en poste (AVUEAP), esquina (AVUEAC) y placa parapetada (AVUEAW). Existen bombas con arandela con tanques de agua de diferentes capacidades: 5 L que bombea hasta 5 m con entrada de 230VAC/24VAC/120VAC (AVWASPT0V5L5M00), 23 L que bombea hasta 11 m con entrada de 230VAC/24VAC/120VAC (AVWASPT0V23L11M00), 23 L que bombea hasta 30 m con entrada de 230VAC (AVWASPT1V23L30M00) y 23 L que bombea hasta 30 m con entrada de 120VAC (AVWASPT3V23L30M00). Adem\u00e1s, hay cajas de comunicaci\u00f3n con fuente de alimentaci\u00f3n e interruptor disponibles para 220 a 230 VAC (AVCOMB100A), 24 VAC (AVCOMB200A) y 120 a 127 VAC (AVCOMB300A). Tambi\u00e9n incluye un protector frente a subidas de tensi\u00f3n de la l\u00ednea Ethernet (AVSURGEPR), una blade de escobilla de repuesto (AVOUEWIPER) y un kit de mantenimiento de la c\u00e1mara que contiene varios componentes esenciales como conectores, prensaestopas de cable, juntas y una llave Allen (AVOUEMAN).", "[TABLA] El modelo H5A PTZ Resistente de la c\u00e1mara de Avigilon incluye la opci\u00f3n de habilitar el modo criptogr\u00e1fico FIPS Nivel 1 con la licencia CAM-FIPS-CRYPTR-L3. Adem\u00e1s, es posible habilitar el modo criptogr\u00e1fico FIPS Nivel 3 con la licencia MSI CRYPTR SD."], "texto": "2 MP 4MP 8 MP CARACTER\u00cdSTICAS RESISTENCIA Y DURACI\u00d3N EXCEPCIONALES Probado seg\u00fan MIL-STD-167-1A y 810G para tolerancia extrema a golpes y vibraciones. Clasificaci\u00f3n IK10 de resistencia a impactos ALTA RESISTENCIA AL VIENTO Resiste vientos de hasta 230 kph (143 mph) si el PTZ se mueve a m\u00e1xima velocidad. FIABILIDAD OPERATIVA PARA SUPERVISAR ELTR\u00c1FICO Cumple con los requisitos ambientales NEMA TS2 para implementaci\u00f3n en aplicaciones de monitoreo de tr\u00e1fico. INSTALACI\u00d3N FLEXIBLE Ofrece muchas opciones de accesorios que le permiten adaptarse a las instalaciones m\u00e1s exigentes, por ejemplo, lossoportes de montaje, lasfuentes de alimentaci\u00f3n, lasbombas de agua, losiluminadores de luz blanca ylosinfrarrojos. RANGO DE TEMPERATURA AMPLIO Registro permanente entre -40\u00b0C y +65 \u00b0C (-40 \u00b0F y +149 \u00b0F). CUMPLIMIENTO DEL EST\u00c1NDAR FIPS 140-2 Aumenta la seguridad de los datos gracias a la criptograf\u00eda compatible con el est\u00e1ndar FIPS que incluyen las c\u00e1maras1. COMPATIBILIDAD CON ONVIF La compatibilidad con los perfiles S y T de ONVIF facilita la integraci\u00f3n con las infraestructuras de ONVIF actuales. Lacompatibilidad con el perfil G admite la b\u00fasqueda, la reproducci\u00f3n y la recuperaci\u00f3n de grabaciones en el extremo. H.264 Y H.265 CON TECNOLOG\u00cdA HDSM SMARTCODEC\u2122 ONVIF es una marca comercial de Onvif, Inc. 1 Opci\u00f3n de comprar la licencia de c\u00e1mara FIPS Nivel 1 o el cifrado basado enhardware CRYPTR microSD y la administraci\u00f3n de claves para soporte ycertificaci\u00f3n FIPS Nivel 3. RENDIMIENTO DE IMAGEN 2,0 MP 4,0MP 8,0MP Sensor de imagen CMOS de barrido progresivo 1/2,8\u201d Sensor CMOS tipo \u201cExmor R\u201d de 1/2,5\u201d P\u00edxeles activos (H x V) 1937 (H) \u00d7 1097 (V) 2688 (H) \u00d7 1512 (V) 3840 (H) \u00d7 2160 (V) \u00c1rea de digitalizaci\u00f3n (H x V) 4,8mm (H) \u00d7 2,7mm (V); 0,189\" (H) \u00d7 0,106\" (V) 6,22 mm (H) \u00d7 3,50 mm (V); 0,245\" (H) \u00d7 0,137\" (V) Distancia m\u00e1xima de iluminaci\u00f3n IR AVUEI8AA 100 m (328 pies) 30 m (98 pies) AVUEI8AAP 200 m (656 pies) 75 m (246 pies) AVUEI9AA 75 m (246 pies) 20 m (66 pies) AVUEIWAA 150 m (492 pies) 50 m (164 pies) AVUEIWAAP 200 m (656 pies) 100 m (328 pies) Iluminaci\u00f3n m\u00ednima 0,03 lux (F/1,6) en modo color; 0,02 lux (F/1,6) en modo monocromo 0,3 lux (F/2,0) en modo color; 0,09 lux (F/2,0) en modo monocromo Rango din\u00e1mico M\u00e1s de 120 dB 100dB Velocidad de imagen Hasta 60fps Hasta 30fps Relaci\u00f3n de aspecto (Escalado de resoluci\u00f3n) Hasta (16:9) 384\u00d7216 o (5:4) 320\u00d7256 Filtro de reducci\u00f3n de ruido 3D S\u00ed OBJETIVO 2,0 MP 4,0MP 8,0MP Objetivo De 4,25 a 170mm, F/1,6 - F/4,95, enfoque autom\u00e1tico De 4,4 a 88mm, F/2,0 - F/3,8, enfoque autom\u00e1tico \u00c1ngulo de visi\u00f3n Horizontal 66,35\u00b0 - 1,9\u00b0 69,7\u00b0 - 2,2\u00b0 Segmento vertical 38,5\u00b0 - 1,1\u00b0 42,8\u00b0 - 1,3\u00b0 Zoom 40x 36x1 CONTROL DE IMAGEN 2,0 MP 4,0MP 8MP Compresi\u00f3n de video H.264 HDSM SmartCodec, H.265 HDSM SmartCodec, Motion JPEG Transmisi\u00f3n Transmisi\u00f3n m\u00faltiple H.264, Transmisi\u00f3n m\u00faltiple H.265, Motion JPEG Detecci\u00f3n de movimiento Movimiento de p\u00edxeles: Umbral y sensibilidad seleccionables. Detecci\u00f3n de objetos clasificados Control electr\u00f3nico del obturador Autom\u00e1tico, manual (de 1/1 a 1/10000 s) Control del diafragma Autom\u00e1tico, abierto, cerrado Control de d\u00eda/noche Autom\u00e1tico, manual Control de parpadeo 60Hz, 50Hz Balance de blancos Autom\u00e1tico, manual Compensaci\u00f3n de contraluz Activar/Desactivar Zonas de privacidad 3D, hasta 64 zonas Preselecciones 500 preselecciones con nombre Rondas 10 rondas con nombre Zoom digital Hasta 100 aumentos cuando se utiliza con ACC\u2122Client Estabilizaci\u00f3n de la imagen electr\u00f3nica No S\u00ed Desempa\u00f1ado digital Ajustable/Desactivado Red 100BASE-TX Conector RJ-45 ONVIF Conformidad con ONVIF Perfil S, Perfil T, y Perfil G (www.onvif.org) Protocolos de transmisi\u00f3n RTP/UDP, RTP/UDP multidifusi\u00f3n, RTP/RTSP/TCP, RTP/RTSP/HTTP/TCP, RTP/RTSP/HTTPS/TCP, HTTP Protocolos de administraci\u00f3n de dispositivos SNMP v2c, SNMP v3 PERIF\u00c9RICOS Entrada/Salida de audio Ninguna Terminales de E/S externos 2 entradas de alarma, 2 salidas de alarma MEC\u00c1NICAS Dimensiones (\u00d8xAl) \u00d8240 mm \u00d7 406 mm; \u00d89,45\u201d \u00d7 16,0\u201d Peso C\u00e1mara 7,1kg (15,6lb) de 5 megap\u00edxeles con iluminador IR 7,4kg (16,3lb) Ventana de cristal Espesor de 6mm (0,24\u201d) Cuerpo Aluminio y tecnopol\u00edmero Carcasa Montaje colgante y en pedestal Finalizar Pintado con epoxy-poli\u00e9ster en polvo, cercano a RAL9002 Barrido vertical Derecho: -90\u00b0 a +90\u00b0; Invertido: -40\u00b0 a +90\u00b0 Hasta 250\u00b0/segundo Barrido horizontal 360\u00b0, infinito, hasta 250\u00b0/segundo EL\u00c9CTRICAS Fuente de alimentaci\u00f3n Fuente de alimentaci\u00f3n externa 24 VDC \u00b110%; o 24 VAC rms \u00b110%, 50 o 60 Hz PoE* PoE de 90 W: Phihong POE90U-1BT6-A-RC (n\u00famero de pieza de Avigilon POE-INJ-BT-90W-NA) Conector de alimentaci\u00f3n Bloque de terminales de dos cables, 18AWG a 13AWG Bater\u00eda de reserva RTC Ninguna MEDIOAMBIENTALES Temperatura de funcionamiento Operaci\u00f3n continua de -40\u00b0C a +65\u00b0C (-40\u00b0F a 149\u00b0F) Temperatura de almacenamiento De -40 \u00b0C a +70 \u00b0C (-40\u00b0F a 158\u00b0F) Humedad Del 5 % al 95 % sin condensaci\u00f3n Puesta en marcha en fr\u00edo Retardo al inicio hasta 135 minutos a temperaturas inferiores a -10\u00b0C (14\u00b0F) Resistencia al viento sostenida de 230km/h (143mph) Certificaciones/Directivas UL, cUL, CE, UKCA, ROHS, RCM, NOM, KC, BIS Seguridad UL 62368-1, CSA 62368-1, IEC/EN 62368-1, IEC/EN 62471 Medioambiente y rendimiento UL/CSA/IEC 60950-22, calificaci\u00f3n de impactos IEC 62262 IK10 (solo para la carcasa), IEC 60529 IP66, IP67, IP68 calificaci\u00f3n clim\u00e1tica, IEC 60068-2-1, IEC 60068-2-2, IEC 60068-2-6, IEC 60068-2-30, NEMA TS 2 para 2.2.7 - 2.2.9, Type 4X and 6P, roc\u00edo salino ASTM B117, ISO 14993, MIL-STD-810-H, MIL-STD-167-1A Inmunidad electromagn\u00e9tica EN 55035, EN 50130-4, EN 50121-4 Garant\u00eda Garant\u00eda limitada de 5 a\u00f1os. Garant\u00eda extendida no disponible. ESPECIFICACIONES DEL AN\u00c1LISIS EVENTOS DE AN\u00c1LISIS ADMITIDOS EN LA POSICI\u00d3N DE INICIO Objetos en el \u00e1rea de inter\u00e9s El evento se activa cuando el tipo de objeto seleccionado se desplaza dentro de la regi\u00f3n de inter\u00e9s. El objeto aparece o entra en el\u00e1rea El evento se activa cada vez que un objeto entra en la regi\u00f3n de inter\u00e9s. Este evento se puede utilizar para contar objetos. Objeto no presente en el \u00e1rea El evento se activa cuando no hay objetos presentes en la regi\u00f3n de inter\u00e9s. Objetos que entran en el \u00e1rea El evento se activa cuando el n\u00famero de objetos especificado ha entrado en la regi\u00f3n de inter\u00e9s. Objetos que abandonan el \u00e1rea El evento se activa cuando el n\u00famero de objetos especificado ha abandonado la regi\u00f3n de inter\u00e9s. El objeto se detiene en el \u00e1rea El evento se activa cuando un objeto se mueve en una regi\u00f3n de inter\u00e9s y luego se detiene durante un periodo de tiempo determinado. Direcci\u00f3n prohibida El evento se activa cuando un objeto se mueve en la direcci\u00f3n prohibida del recorrido. Detecci\u00f3n de alteraci\u00f3n El evento se activa cuando la escena cambia de manera inesperada. SEGUIMIENTO AUTOM\u00c1TICO DE OBJETOS EN EL \u00c1REA DE INTER\u00c9S Seguimiento autom\u00e1tico de objetos en el \u00e1rea de inter\u00e9s TIPOS DE OBJETOS CLASIFICADOS ADMITIDOS Tipos de objetos en modo exterior Veh\u00edculo, subtipos: Coche, cami\u00f3n, bicicleta, motocicleta, autob\u00fas Persona Tipos de objetos en modo interior Persona ENSE\u00d1AR CON EL EJEMPLO Ense\u00f1ar con el ejemplo S\u00ed, cuando se utiliza con Avigilon Control Center\u2122 FUNCIONES COMPATIBLES CON VERSIONES DE AVIGILON CONTROL CENTER (ACC) ACC Versi\u00f3n 6.14.12 osuperior* ACC Versi\u00f3n7.14.0 o superior** X MM (H5A-RGDPTZ-DP) INFORMACI\u00d3N DEL PEDIDO C\u00c1MARAS PTZ MP WDR TECNOLOG\u00cdA LIGHTCATCHER AN\u00c1LISIS EN LA POSICI\u00d3N DE INICIO OBJETIVO ZOOM IP66/67/68 2.0C-H5A-RGDPTZ-DP36B 2.0 4,25 - 170 mm 40x* 4.0C-H5A-RGDPTZ-DP36 4,0 4,4 - 88 mm 36x* 8.0C-H5A-RGDPTZ-DP36 8,0 4,4 - 88 mm 36x* ACCESORIOS PARA C\u00c1MARA PTZ ACCESORIOS DESCRIPCI\u00d3N POE-INJ-BT-90W-NA Inyector PoE Gigabit 802.3bt de 90 W, puerto \u00fanico AVUEI8AA Iluminador IR, 850nm, compatible con H5A Rugged PTZ, cercano a RAL9002 AVUEI8AAP Iluminador IR de larga distancia, 850nm, compatible con H5A Rugged PTZ, cercano a RAL9002 AVUEI9AA Iluminador IR, 940nm, compatible con H5A Rugged PTZ, cercano a RAL9002 AVUEIWAA Iluminador de luz blanca, compatible con H5A Rugged PTZ, cercano a RAL9002 AVUEIWAAP Iluminador de luz blanca de larga distancia, compatible con H5A Rugged PTZ, cercano a RAL9002 AVUEBWAA Montaje de brazo de pared, compatible con H5A Rugged PTZ, cercano a RAL9002 AVUEBP0AA Soporte de montaje parapetado, canal de cable interno, compatible con H5A Rugged PTZ, cercano a RAL9002 AVUEAP Adaptador de montaje en poste, acero inoxidable AISI316L, compatible con montaje con brazo para pared AVUEBWAA AVUEAC Adaptador de montaje en esquina, acero inoxidable AISI316L, compatible con montaje con brazo para pared AVUEBWAA AVWASPT0V5L5M00 Bomba con arandela, tanque de agua de 5L, bombea hasta 5m (16,4 pies), entrada de 230VAC/24VAC/120VAC, compatible con H5A Rugged PTZ AVWASPT0V23L11M00 Bomba con arandela, tanque de agua de 23L, bombea hasta 11m (36 pies), entrada de 230VAC/24VAC/120VAC, compatible con H5A Rugged PTZ AVWASPT1V23L30M00 Bomba con arandela, tanque de agua de 23L, bombea hasta 30m (98 pies), entrada de 230VAC, compatible con H5A Rugged PTZ AVWASPT3V23L30M00 Bomba con arandela, tanque de agua de 23L, bombea hasta 30m (98 pies), entrada de 120VAC, compatible con H5A Rugged PTZ AVCOMB100A Caja de comunicaci\u00f3n con fuente de alimentaci\u00f3n e interruptor, 220 a 230VAC, policarbonato, compatible con H5A Rugged PTZ AVCOMB200A Caja de comunicaci\u00f3n con fuente de alimentaci\u00f3n e interruptor, 24VAC, policarbonato, compatible con H5A Rugged PTZ AVCOMB300A Caja de comunicaci\u00f3n con fuente de alimentaci\u00f3n e interruptor, 120 a 127 VAC, policarbonato, compatible con H5A Rugged PTZ AVSURGEPR Protector frente a subidas de tensi\u00f3n de la l\u00ednea Ethernet AVOUEWIPER Blade de escobilla de repuesto ACCESORIOS Y LICENCIAS DE C\u00c1MARA OPCIONALES CAM-FIPS Licencia de c\u00e1mara para habilitar el modo criptogr\u00e1fico FIPS Nivel 1 en cualquier c\u00e1mara H5A CAM-FIPS-CRYPTR-L3 MSI CRYPTR SD con licencia de c\u00e1mara para habilitar el modo criptogr\u00e1fico FIPS Nivel 3 en cualquier c\u00e1mara H5A1 1 No incluye l\u00ednea de c\u00e1mara con protecci\u00f3n ante explosiones H5A.", "texto_traducido": "2 MP 4MP 8 MP CARACTER\u00cdSTICAS RESISTENCIA Y DURACI\u00d3N EXCEPCIONALES Probado seg\u00fan MIL-STD-167-1A y 810G para tolerancia extrema a golpes y vibraciones. Clasificaci\u00f3n IK10 de resistencia a impactos ALTA RESISTENCIA AL VIENTO Resiste vientos de hasta 230 kph (143 mph) si el PTZ se mueve a m\u00e1xima velocidad. FIABILIDAD OPERATIVA PARA SUPERVISAR ELTR\u00c1FICO Cumple con los requisitos ambientales NEMA TS2 para implementaci\u00f3n en aplicaciones de monitoreo de tr\u00e1fico. INSTALACI\u00d3N FLEXIBLE Ofrece muchas opciones de accesorios que le permiten adaptarse a las instalaciones m\u00e1s exigentes, por ejemplo, lossoportes de montaje, lasfuentes de alimentaci\u00f3n, lasbombas de agua, losiluminadores de luz blanca ylosinfrarrojos. RANGO DE TEMPERATURA AMPLIO Registro permanente entre -40\u00b0C y +65 \u00b0C (-40 \u00b0F y +149 \u00b0F). CUMPLIMIENTO DEL EST\u00c1NDAR FIPS 140-2 Aumenta la seguridad de los datos gracias a la criptograf\u00eda compatible con el est\u00e1ndar FIPS que incluyen las c\u00e1maras1. COMPATIBILIDAD CON ONVIF La compatibilidad con los perfiles S y T de ONVIF facilita la integraci\u00f3n con las infraestructuras de ONVIF actuales. Lacompatibilidad con el perfil G admite la b\u00fasqueda, la reproducci\u00f3n y la recuperaci\u00f3n de grabaciones en el extremo. H.264 Y H.265 CON TECNOLOG\u00cdA HDSM SMARTCODEC\u2122 ONVIF es una marca comercial de Onvif, Inc. 1 Opci\u00f3n de comprar la licencia de c\u00e1mara FIPS Nivel 1 o el cifrado basado enhardware CRYPTR microSD y la administraci\u00f3n de claves para soporte ycertificaci\u00f3n FIPS Nivel 3. RENDIMIENTO DE IMAGEN 2,0 MP 4,0MP 8,0MP Sensor de imagen CMOS de barrido progresivo 1/2,8\u201d Sensor CMOS tipo \u201cExmor R\u201d de 1/2,5\u201d P\u00edxeles activos (H x V) 1937 (H) \u00d7 1097 (V) 2688 (H) \u00d7 1512 (V) 3840 (H) \u00d7 2160 (V) \u00c1rea de digitalizaci\u00f3n (H x V) 4,8mm (H) \u00d7 2,7mm (V); 0,189\" (H) \u00d7 0,106\" (V) 6,22 mm (H) \u00d7 3,50 mm (V); 0,245\" (H) \u00d7 0,137\" (V) Distancia m\u00e1xima de iluminaci\u00f3n IR AVUEI8AA 100 m (328 pies) 30 m (98 pies) AVUEI8AAP 200 m (656 pies) 75 m (246 pies) AVUEI9AA 75 m (246 pies) 20 m (66 pies) AVUEIWAA 150 m (492 pies) 50 m (164 pies) AVUEIWAAP 200 m (656 pies) 100 m (328 pies) Iluminaci\u00f3n m\u00ednima 0,03 lux (F/1,6) en modo color; 0,02 lux (F/1,6) en modo monocromo 0,3 lux (F/2,0) en modo color; 0,09 lux (F/2,0) en modo monocromo Rango din\u00e1mico M\u00e1s de 120 dB 100dB Velocidad de imagen Hasta 60fps Hasta 30fps Relaci\u00f3n de aspecto (Escalado de resoluci\u00f3n) Hasta (16:9) 384\u00d7216 o (5:4) 320\u00d7256 Filtro de reducci\u00f3n de ruido 3D S\u00ed OBJETIVO 2,0 MP 4,0MP 8,0MP Objetivo De 4,25 a 170mm, F/1,6 - F/4,95, enfoque autom\u00e1tico De 4,4 a 88mm, F/2,0 - F/3,8, enfoque autom\u00e1tico \u00c1ngulo de visi\u00f3n Horizontal 66,35\u00b0 - 1,9\u00b0 69,7\u00b0 - 2,2\u00b0 Segmento vertical 38,5\u00b0 - 1,1\u00b0 42,8\u00b0 - 1,3\u00b0 Zoom 40x 36x1 CONTROL DE IMAGEN 2,0 MP 4,0MP 8MP Compresi\u00f3n de video H.264 HDSM SmartCodec, H.265 HDSM SmartCodec, Motion JPEG Transmisi\u00f3n Transmisi\u00f3n m\u00faltiple H.264, Transmisi\u00f3n m\u00faltiple H.265, Motion JPEG Detecci\u00f3n de movimiento Movimiento de p\u00edxeles: Umbral y sensibilidad seleccionables. Detecci\u00f3n de objetos clasificados Control electr\u00f3nico del obturador Autom\u00e1tico, manual (de 1/1 a 1/10000 s) Control del diafragma Autom\u00e1tico, abierto, cerrado Control de d\u00eda/noche Autom\u00e1tico, manual Control de parpadeo 60Hz, 50Hz Balance de blancos Autom\u00e1tico, manual Compensaci\u00f3n de contraluz Activar/Desactivar Zonas de privacidad 3D, hasta 64 zonas Preselecciones 500 preselecciones con nombre Rondas 10 rondas con nombre Zoom digital Hasta 100 aumentos cuando se utiliza con ACC\u2122Client Estabilizaci\u00f3n de la imagen electr\u00f3nica No S\u00ed Desempa\u00f1ado digital Ajustable/Desactivado Red 100BASE-TX Conector RJ-45 ONVIF Conformidad con ONVIF Perfil S, Perfil T, y Perfil G (www.onvif.org) Protocolos de transmisi\u00f3n RTP/UDP, RTP/UDP multidifusi\u00f3n, RTP/RTSP/TCP, RTP/RTSP/HTTP/TCP, RTP/RTSP/HTTPS/TCP, HTTP Protocolos de administraci\u00f3n de dispositivos SNMP v2c, SNMP v3 PERIF\u00c9RICOS Entrada/Salida de audio Ninguna Terminales de E/S externos 2 entradas de alarma, 2 salidas de alarma MEC\u00c1NICAS Dimensiones (\u00d8xAl) \u00d8240 mm \u00d7 406 mm; \u00d89,45\u201d \u00d7 16,0\u201d Peso C\u00e1mara 7,1kg (15,6lb) de 5 megap\u00edxeles con iluminador IR 7,4kg (16,3lb) Ventana de cristal Espesor de 6mm (0,24\u201d) Cuerpo Aluminio y tecnopol\u00edmero Carcasa Montaje colgante y en pedestal Finalizar Pintado con epoxy-poli\u00e9ster en polvo, cercano a RAL9002 Barrido vertical Derecho: -90\u00b0 a +90\u00b0; Invertido: -40\u00b0 a +90\u00b0 Hasta 250\u00b0/segundo Barrido horizontal 360\u00b0, infinito, hasta 250\u00b0/segundo EL\u00c9CTRICAS Fuente de alimentaci\u00f3n Fuente de alimentaci\u00f3n externa 24 VDC \u00b110%; o 24 VAC rms \u00b110%, 50 o 60 Hz PoE* PoE de 90 W: Phihong POE90U-1BT6-A-RC (n\u00famero de pieza de Avigilon POE-INJ-BT-90W-NA) Conector de alimentaci\u00f3n Bloque de terminales de dos cables, 18AWG a 13AWG Bater\u00eda de reserva RTC Ninguna MEDIOAMBIENTALES Temperatura de funcionamiento Operaci\u00f3n continua de -40\u00b0C a +65\u00b0C (-40\u00b0F a 149\u00b0F) Temperatura de almacenamiento De -40 \u00b0C a +70 \u00b0C (-40\u00b0F a 158\u00b0F) Humedad Del 5 % al 95 % sin condensaci\u00f3n Puesta en marcha en fr\u00edo Retardo al inicio hasta 135 minutos a temperaturas inferiores a -10\u00b0C (14\u00b0F) Resistencia al viento sostenida de 230km/h (143mph) Certificaciones/Directivas UL, cUL, CE, UKCA, ROHS, RCM, NOM, KC, BIS Seguridad UL 62368-1, CSA 62368-1, IEC/EN 62368-1, IEC/EN 62471 Medioambiente y rendimiento UL/CSA/IEC 60950-22, calificaci\u00f3n de impactos IEC 62262 IK10 (solo para la carcasa), IEC 60529 IP66, IP67, IP68 calificaci\u00f3n clim\u00e1tica, IEC 60068-2-1, IEC 60068-2-2, IEC 60068-2-6, IEC 60068-2-30, NEMA TS 2 para 2.2.7 - 2.2.9, Type 4X and 6P, roc\u00edo salino ASTM B117, ISO 14993, MIL-STD-810-H, MIL-STD-167-1A Inmunidad electromagn\u00e9tica EN 55035, EN 50130-4, EN 50121-4 Garant\u00eda Garant\u00eda limitada de 5 a\u00f1os. Garant\u00eda extendida no disponible. ESPECIFICACIONES DEL AN\u00c1LISIS EVENTOS DE AN\u00c1LISIS ADMITIDOS EN LA POSICI\u00d3N DE INICIO Objetos en el \u00e1rea de inter\u00e9s El evento se activa cuando el tipo de objeto seleccionado se desplaza dentro de la regi\u00f3n de inter\u00e9s. El objeto aparece o entra en el\u00e1rea El evento se activa cada vez que un objeto entra en la regi\u00f3n de inter\u00e9s. Este evento se puede utilizar para contar objetos. Objeto no presente en el \u00e1rea El evento se activa cuando no hay objetos presentes en la regi\u00f3n de inter\u00e9s. Objetos que entran en el \u00e1rea El evento se activa cuando el n\u00famero de objetos especificado ha entrado en la regi\u00f3n de inter\u00e9s. Objetos que abandonan el \u00e1rea El evento se activa cuando el n\u00famero de objetos especificado ha abandonado la regi\u00f3n de inter\u00e9s. El objeto se detiene en el \u00e1rea El evento se activa cuando un objeto se mueve en una regi\u00f3n de inter\u00e9s y luego se detiene durante un periodo de tiempo determinado. Direcci\u00f3n prohibida El evento se activa cuando un objeto se mueve en la direcci\u00f3n prohibida del recorrido. Detecci\u00f3n de alteraci\u00f3n El evento se activa cuando la escena cambia de manera inesperada. SEGUIMIENTO AUTOM\u00c1TICO DE OBJETOS EN EL \u00c1REA DE INTER\u00c9S Seguimiento autom\u00e1tico de objetos en el \u00e1rea de inter\u00e9s TIPOS DE OBJETOS CLASIFICADOS ADMITIDOS Tipos de objetos en modo exterior Veh\u00edculo, subtipos: Coche, cami\u00f3n, bicicleta, motocicleta, autob\u00fas Persona Tipos de objetos en modo interior Persona ENSE\u00d1AR CON EL EJEMPLO Ense\u00f1ar con el ejemplo S\u00ed, cuando se utiliza con Avigilon Control Center\u2122 FUNCIONES COMPATIBLES CON VERSIONES DE AVIGILON CONTROL CENTER (ACC) ACC Versi\u00f3n 6.14.12 osuperior* ACC Versi\u00f3n7.14.0 o superior** X MM (H5A-RGDPTZ-DP) INFORMACI\u00d3N DEL PEDIDO C\u00c1MARAS PTZ MP WDR TECNOLOG\u00cdA LIGHTCATCHER AN\u00c1LISIS EN LA POSICI\u00d3N DE INICIO OBJETIVO ZOOM IP66/67/68 2.0C-H5A-RGDPTZ-DP36B 2.0 4,25 - 170 mm 40x* 4.0C-H5A-RGDPTZ-DP36 4,0 4,4 - 88 mm 36x* 8.0C-H5A-RGDPTZ-DP36 8,0 4,4 - 88 mm 36x* ACCESORIOS PARA C\u00c1MARA PTZ ACCESORIOS DESCRIPCI\u00d3N POE-INJ-BT-90W-NA Inyector PoE Gigabit 802.3bt de 90 W, puerto \u00fanico AVUEI8AA Iluminador IR, 850nm, compatible con H5A Rugged PTZ, cercano a RAL9002 AVUEI8AAP Iluminador IR de larga distancia, 850nm, compatible con H5A Rugged PTZ, cercano a RAL9002 AVUEI9AA Iluminador IR, 940nm, compatible con H5A Rugged PTZ, cercano a RAL9002 AVUEIWAA Iluminador de luz blanca, compatible con H5A Rugged PTZ, cercano a RAL9002 AVUEIWAAP Iluminador de luz blanca de larga distancia, compatible con H5A Rugged PTZ, cercano a RAL9002 AVUEBWAA Montaje de brazo de pared, compatible con H5A Rugged PTZ, cercano a RAL9002 AVUEBP0AA Soporte de montaje parapetado, canal de cable interno, compatible con H5A Rugged PTZ, cercano a RAL9002 AVUEAP Adaptador de montaje en poste, acero inoxidable AISI316L, compatible con montaje con brazo para pared AVUEBWAA AVUEAC Adaptador de montaje en esquina, acero inoxidable AISI316L, compatible con montaje con brazo para pared AVUEBWAA AVWASPT0V5L5M00 Bomba con arandela, tanque de agua de 5L, bombea hasta 5m (16,4 pies), entrada de 230VAC/24VAC/120VAC, compatible con H5A Rugged PTZ AVWASPT0V23L11M00 Bomba con arandela, tanque de agua de 23L, bombea hasta 11m (36 pies), entrada de 230VAC/24VAC/120VAC, compatible con H5A Rugged PTZ AVWASPT1V23L30M00 Bomba con arandela, tanque de agua de 23L, bombea hasta 30m (98 pies), entrada de 230VAC, compatible con H5A Rugged PTZ AVWASPT3V23L30M00 Bomba con arandela, tanque de agua de 23L, bombea hasta 30m (98 pies), entrada de 120VAC, compatible con H5A Rugged PTZ AVCOMB100A Caja de comunicaci\u00f3n con fuente de alimentaci\u00f3n e interruptor, 220 a 230VAC, policarbonato, compatible con H5A Rugged PTZ AVCOMB200A Caja de comunicaci\u00f3n con fuente de alimentaci\u00f3n e interruptor, 24VAC, policarbonato, compatible con H5A Rugged PTZ AVCOMB300A Caja de comunicaci\u00f3n con fuente de alimentaci\u00f3n e interruptor, 120 a 127 VAC, policarbonato, compatible con H5A Rugged PTZ AVSURGEPR Protector frente a subidas de tensi\u00f3n de la l\u00ednea Ethernet AVOUEWIPER Blade de escobilla de repuesto ACCESORIOS Y LICENCIAS DE C\u00c1MARA OPCIONALES CAM-FIPS Licencia de c\u00e1mara para habilitar el modo criptogr\u00e1fico FIPS Nivel 1 en cualquier c\u00e1mara H5A CAM-FIPS-CRYPTR-L3 MSI CRYPTR SD con licencia de c\u00e1mara para habilitar el modo criptogr\u00e1fico FIPS Nivel 3 en cualquier c\u00e1mara H5A1 1 No incluye l\u00ednea de c\u00e1mara con protecci\u00f3n ante explosiones H5A."}